mysite/__init__.py
mysite/asgi.py
mysite/settings.py
mysite/urls.py
mysite/wsgi.py
mysite/templates/admin/filter.html
polls/__init__.py
polls/admin.py
polls/apps.py
polls/models.py
polls/tests.py
polls/urls.py
polls/views.py
polls/migrations/0001_initial.py
polls/migrations/__init__.py
polls/static/polls/global.css
polls/templates/polls/layout.html
polls/templates/polls/question_detail.html
polls/templates/polls/question_list.html
polls/templates/polls/results.html
it_11_23_django-0.1.0.dist-info/METADATA
it_11_23_django-0.1.0.dist-info/WHEEL
it_11_23_django-0.1.0.dist-info/RECORD
