Metadata-Version: 2.4
Name: it-11-23-django
Version: 0.1.0
Summary: Tutorial App
Requires-Python: >=3.12
Requires-Dist: django-daisy>=1.0.14
Requires-Dist: django-jazzmin>=3.0.1
Requires-Dist: django>=5.1.6
